weather_notify-1.0.1.dist-info/METADATA
weather_notify-1.0.1.dist-info/RECORD
weather_notify-1.0.1.dist-info/WHEEL
weather_notify-1.0.1.dist-info/entry_points.txt
weather_notify-1.0.1.dist-info/top_level.txt
weathernotifier/__init__.py
weathernotifier/location.py
weathernotifier/notifier.py
weathernotifier/weather.py
