Metadata-Version: 2.1
Name: weather-notify
Version: 1.0.1
Summary: Shows weather details
Home-page: https://github.com/dushyantRathore/Weather-Notifier
Author: Dushyant Rathore
Author-email: dushyant.bgs@gmail.com
License: MIT
Keywords: Weather notification tool
Platform: UNKNOWN
Classifier: Development Status :: 3 - Alpha
Classifier: Environment :: Console
Classifier: Intended Audience :: Developers
Classifier: Intended Audience :: Information Technology
Classifier: Natural Language :: English
Classifier: Topic :: Software Development :: Build Tools
Classifier: License :: OSI Approved :: MIT License
Classifier: Programming Language :: Python :: 2
Classifier: Programming Language :: Python :: 2.6
Classifier: Programming Language :: Python :: 2.7
Requires-Dist: reverse-geocoder
Requires-Dist: requests (==2.18.2)
Requires-Dist: pyowm
Requires-Dist: notify2
